{
  "teams": [
    {
      "name": "",
      "abbr": "",
      "players": [
        {},
        {},
        {},
        {},
        {},
        {}
      ],
      "game_points": 0,
      "match_points": 0
    },
    {
      "name": "",
      "abbr": "",
      "players": [
        {},
        {},
        {},
        {},
        {},
        {}
      ],
      "game_points": 0,
      "match_points": 0

    },
    {
      "name": "",
      "abbr": "",
      "players": [
        {},
        {},
        {},
        {},
        {},
        {}
      ],
      "game_points": 0,
      "match_points": 0

    },
    {
      "name": "",
      "abbr": "",
      "players": [
        {},
        {},
        {},
        {},
        {},
        {}
      ],
      "game_points": 0,
      "match_points": 0
    }
  ]

}